README.md
setup.py
admix/README.rst
admix/__init__.py
admix/admix.py
admix/admix_fraction.py
admix/admix_models.py
admix/raw_data_processing.py
admix.egg-info/PKG-INFO
admix.egg-info/SOURCES.txt
admix.egg-info/dependency_links.txt
admix.egg-info/entry_points.txt
admix.egg-info/requires.txt
admix.egg-info/top_level.txt
admix/data/E11.11.F
admix/data/E11.alleles
admix/data/K12b.12.F
admix/data/K12b.alleles
admix/data/K7b.7.F
admix/data/K7b.alleles
admix/data/demo_genome_23andme.txt
admix/data/globe13.13.F
admix/data/globe13.alleles
admix/data/world9.9.F
admix/data/world9.alleles