Metadata-Version: 1.1
Name: admix
Version: 1.1
Summary: An admixture analysis tool that supports raw data from 23andme, AncestryDNA, etc.
Home-page: https://github.com/stevenliuyi/admix
Author: Steven Liu
Author-email: me@yliu.io
License: GNU General Public License v3.0
Keywords: bio DNA SNP ancestry admixture
Platform: UNKNOWN
Classifier: License :: OSI Approved :: GNU General Public License v3 (GPLv3)
Classifier: Environment :: Console
Classifier: Intended Audience :: Science/Research
Classifier: Natural Language :: English
Classifier: Natural Language :: Chinese (Simplified)
Classifier: Programming Language :: Python :: 2
Classifier: Programming Language :: Python :: 2.7
Classifier: Programming Language :: Python :: 3
Classifier: Programming Language :: Python :: 3.5
Classifier: Programming Language :: Python :: 3.6
Classifier: Topic :: Scientific/Engineering :: Bio-Informatics
